xlmhglite/__init__.py
xlmhglite/mhg.py
xlmhglite/mhg_cython.cp311-win_amd64.pyd
xlmhglite/result.py
xlmhglite/test.py
xlmhglite/visualize.py
xlmhglite-1.1.1.dist-info/LICENSE
xlmhglite-1.1.1.dist-info/METADATA
xlmhglite-1.1.1.dist-info/WHEEL
xlmhglite-1.1.1.dist-info/top_level.txt
xlmhglite-1.1.1.dist-info/RECORD
