Metadata-Version: 2.1
Name: xlmhglite
Version: 1.1.1
Summary: XL-mHG lite: A light implementation of the Semiparametric Enrichment Test
Home-page: https://github.com/GuyTeichman/xlmhglite
Author: Guy Teichman
Author-email: guyteichman@gmail.com
License: GPLv3
Keywords: statistics,nonparametric,semiparametric,enrichment test,ranked lists
Classifier: Development Status :: 5 - Production/Stable
Classifier: Intended Audience :: Developers
Classifier: Intended Audience :: Science/Research
Classifier: Topic :: Scientific/Engineering :: Bio-Informatics
Classifier: License :: OSI Approved :: BSD License
Classifier: Programming Language :: Python :: 3.9
Classifier: Programming Language :: Python :: 3.10
Classifier: Programming Language :: Python :: 3.11
Classifier: Programming Language :: Python :: 3.12
Classifier: Programming Language :: Cython
Requires-Python: >=3.9
License-File: LICENSE
Requires-Dist: numpy
Requires-Dist: cython
Provides-Extra: all
Requires-Dist: plotly ; extra == 'all'
